cloudability_api/__init__.py
cloudability_api/client.py
cloudability_api/reports.py
cloudability_api/rightsizing.py
cloudability_api/rightsizing_roi.py
cloudability_api/views.py
cloudability_api-0.0.1.dist-info/METADATA
cloudability_api-0.0.1.dist-info/WHEEL
cloudability_api-0.0.1.dist-info/licenses/LICENSE
cloudability_api-0.0.1.dist-info/RECORD
