Metadata-Version: 2.4
Name: cloudability-api
Version: 0.0.1
Summary: A Python wrapper for the Cloudability API
Project-URL: Homepage, https://github.com/yourusername/cloudability-api
Project-URL: Repository, https://github.com/yourusername/cloudability-api
Project-URL: Issues, https://github.com/yourusername/cloudability-api/issues
Author-email: Laurent Dumont <laurentfdumont@coldnorthadmin.com>
License:                     GNU GENERAL PUBLIC LICENSE
License-File: LICENSE
Requires-Python: >=3.8
Requires-Dist: requests
